LICENSE
MANIFEST.in
README.rst
setup.py
django_statsd_patches/__init__.py
django_statsd_patches/tests.py
django_statsd_patches.egg-info/PKG-INFO
django_statsd_patches.egg-info/SOURCES.txt
django_statsd_patches.egg-info/dependency_links.txt
django_statsd_patches.egg-info/not-zip-safe
django_statsd_patches.egg-info/pbr.json
django_statsd_patches.egg-info/requires.txt
django_statsd_patches.egg-info/top_level.txt
django_statsd_patches/patches/__init__.py
django_statsd_patches/patches/redis_timing.py
django_statsd_patches/patches/template.py