Metadata-Version: 1.1
Name: django-statsd-patches
Version: 0.0.6
Summary: Patch and time some additional django libraries
Home-page: https://github.com/streeter/django-statsd-patches
Author: Chris Streeter
Author-email: chris@chrisstreeter.com
License: Copyright (c) 2013 Chris Streeter
